slackagents/__init__.py
slackagents/__main__.py
slackagents/agent/__init__.py
slackagents/agent/assistant.py
slackagents/agent/base.py
slackagents/agent/executor.py
slackagents/agent/slack_assistant.py
slackagents/agent/slack_dm_agent.py
slackagents/agent/slack_workflow_agent.py
slackagents/agent/workflow_agent.py
slackagents/cli/__init__.py
slackagents/cli/add_agent.py
slackagents/cli/config.py
slackagents/cli/create_agent.py
slackagents/cli/delete_agent.py
slackagents/cli/list_agent.py
slackagents/cli/start_agent.py
slackagents/cli/stop_agent.py
slackagents/commons/__init__.py
slackagents/commons/common_types.py
slackagents/commons/configuration_schemas.py
slackagents/commons/default_prompts.py
slackagents/commons/meta_schemas.py
slackagents/commons/prompts/__init__.py
slackagents/commons/prompts/assistant_template.md
slackagents/commons/prompts/get_thread_history_function_prompt.py
slackagents/commons/prompts/meta_prompts.py
slackagents/commons/prompts/restart_function_prompt.py
slackagents/commons/prompts/send_message_function_prompt.py
slackagents/commons/prompts/transition_function_prompt.py
slackagents/commons/prompts/wait_function_prompt.py
slackagents/commons/slack_manifests/example.json
slackagents/commons/slackagent_auto.py
slackagents/graph/__init__.py
slackagents/graph/base.py
slackagents/graph/execution_graph.py
slackagents/graph/states/respond.py
slackagents/llms/__init__.py
slackagents/llms/base.py
slackagents/llms/configs.py
slackagents/llms/openai.py
slackagents/session/__init__.py
slackagents/session/base.py
slackagents/session/session_store.py
slackagents/session/slack_session.py
slackagents/session/utils.py
slackagents/slack/__init__.py
slackagents/slack/handler.py
slackagents/slack/slack_agent_runner.py
slackagents/slack/utils.py
slackagents/tools/__init__.py
slackagents/tools/base.py
slackagents/tools/function_tool.py
slackagents/tools/openapi_tool.py
slackagents/tools/schema.py
slackagents/tools/slack_agent_tools.py
slackagents-0.0.2.dist-info/LICENSE
slackagents-0.0.2.dist-info/LICENSE.txt
slackagents-0.0.2.dist-info/METADATA
slackagents-0.0.2.dist-info/WHEEL
slackagents-0.0.2.dist-info/entry_points.txt
slackagents-0.0.2.dist-info/RECORD
