Metadata-Version: 2.1
Name: slackagents
Version: 0.0.2
Summary: scalable management and collaboration for massive Slack AI agents
Author: Weiran Yao
Author-email: weirayao@gmail.com
Requires-Python: >=3.12,<=3.13
Classifier: Programming Language :: Python :: 3
Classifier: Programming Language :: Python :: 3.12
Requires-Dist: docstring-parser (>=0.16,<0.17)
Requires-Dist: litellm (>=1.48.19,<2.0.0)
Requires-Dist: matplotlib (>=3.9.2,<4.0.0)
Requires-Dist: networkx (>=3.3,<4.0)
Requires-Dist: poetry (>=1.8.3,<2.0.0)
Requires-Dist: python-dotenv (>=1.0.1,<2.0.0)
Requires-Dist: slack-bolt (>=1.21.0,<2.0.0)
Requires-Dist: slack-sdk (>=3.33.1,<4.0.0)
Requires-Dist: tabulate (>=0.9.0,<0.10.0)
Requires-Dist: termcolor (>=2.5.0,<3.0.0)
Project-URL: Documentation, https://docs.slackagents.com
Project-URL: Homepage, https://github.com/SalesforceAIResearch/SlackAgents
Project-URL: Repository, https://github.com/SalesforceAIResearch/SlackAgents
